MANIFEST.in
README.md
setup.py
chinesestockapi.egg-info/PKG-INFO
chinesestockapi.egg-info/SOURCES.txt
chinesestockapi.egg-info/dependency_links.txt
chinesestockapi.egg-info/top_level.txt
cstock/__init__.py
cstock/base_engine.py
cstock/hexun_engine.py
cstock/model.py
cstock/request.py
cstock/sina_engine.py
cstock/yahoo_engine.py
test/test_hexun.py
test/test_model.py
test/test_request.py
test/test_sina.py
test/test_yahoo.py