Metadata-Version: 1.0
Name: chinesestockapi
Version: 1.3
Summary: Python API to get Chinese stock price
Home-page: https://pypi.python.org/pypi/chinesestockapi
Author: Walt Chen
Author-email: godsarmycy@gmail.com
License: UNKNOWN
Platform: any
